{
  "updatedAt": "2026-02-11T18:10:40.399Z",
  "channels": {
    "channelA": [
      {
        "videoId": "e6AixMiItJ8",
        "title": "#3【Quarantine Zone】DAY17から！拳銃で自分の身を守れってこと！？検査しながら！？【天硝路ろまん / StellArt.】",
        "thumbnail": "https://i.ytimg.com/vi/e6AixMiItJ8/hqdefault.jpg",
        "url": "https://www.youtube.com/watch?v=e6AixMiItJ8",
        "status": "live",
        "scheduledStartTime": null,
        "actualStartTime": "2026-02-11T12:59:32Z",
        "actualEndTime": null
      }
    ],
    "channelB": [
      {
        "videoId": "koDOl2J4uvI",
        "title": "【 #アークナイツエンドフィールド 】#5 メインストーリー進める！探索レベルを上げたいいい【華鉈イオ/StellArt.】",
        "thumbnail": "https://i.ytimg.com/vi/koDOl2J4uvI/hqdefault.jpg",
        "url": "https://www.youtube.com/watch?v=koDOl2J4uvI",
        "status": "upcoming",
        "scheduledStartTime": "2026-02-12T13:00:00Z",
        "actualStartTime": null,
        "actualEndTime": null
      }
    ]
  }
}