{
  "updatedAt": "2026-01-23T15:52:41.907Z",
  "channels": {
    "channelA": [
      {
        "videoId": "9JpXCtujdiM",
        "title": "#15【キャプテン翼 RISE OF NEW CHAMPIONS】『EPISODE OF NEW HERO』武蔵中編！アルゼンチン戦勝てるか、、？※ネタバレ注意【天硝路ろまん / StellArt.】",
        "thumbnail": "https://i.ytimg.com/vi/9JpXCtujdiM/hqdefault.jpg",
        "url": "https://www.youtube.com/watch?v=9JpXCtujdiM",
        "status": "live",
        "scheduledStartTime": null,
        "actualStartTime": "2026-01-23T12:59:27Z",
        "actualEndTime": null
      }
    ],
    "channelB": []
  }
}